allen_s_interval_algebra/__init__.py
allen_s_interval_algebra-0.1.0.dist-info/WHEEL
allen_s_interval_algebra-0.1.0.dist-info/METADATA
allen_s_interval_algebra-0.1.0.dist-info/RECORD
