Metadata-Version: 2.1
Name: allen-s-interval-algebra
Version: 0.1.0
Summary: Implementation of the Allen's interval algebra
License: GPL-3.0+
Author: Tanguy Le Carrour
Author-email: tanguy@bioneland.org
Requires-Python: >=3.7,<4.0
Classifier: License :: OSI Approved :: GNU General Public License v3 or later (GPLv3+)
Classifier: Programming Language :: Python :: 3
Classifier: Programming Language :: Python :: 3.7
Requires-Dist: pytz (>=2019.1,<2020.0)
